hacktcha/__init__.py
hacktcha/__main__.py
hacktcha/conf.py
hacktcha/generator/__init__.py
hacktcha/generator/base.py
hacktcha/generator/eastmoney.py
hacktcha/model.py
hacktcha/server.py
hacktcha-0.2.2.dist-info/WHEEL
hacktcha-0.2.2.dist-info/METADATA
hacktcha-0.2.2.dist-info/RECORD
